covenant/__init__.py
covenant/classes/__init__.py
covenant/classes/collect.py
covenant/classes/config.py
covenant/classes/controls.py
covenant/classes/covenant_collector.py
covenant/classes/exceptions.py
covenant/classes/filters.py
covenant/classes/label.py
covenant/classes/metrictypes.py
covenant/classes/plugins.py
covenant/classes/target.py
covenant/filters/__init__.py
covenant/filters/fbuiltins.py
covenant/filters/fbuiltintypes.py
covenant/filters/fjmespath.py
covenant/filters/fmath.py
covenant/filters/fospath.py
covenant/filters/fpyjq.py
covenant/filters/fregex.py
covenant/filters/ftime.py
covenant/modules/__init__.py
covenant/modules/metrics.py
covenant/modules/probes.py
covenant/plugins/__init__.py
covenant/plugins/http.py
covenant/plugins/pfilestat.py
covenant/plugins/predis.py
covenant/plugins/pssl.py
covenant-0.0.65.data/scripts/covenant
covenant-0.0.65.dist-info/LICENSE
covenant-0.0.65.dist-info/METADATA
covenant-0.0.65.dist-info/WHEEL
covenant-0.0.65.dist-info/top_level.txt
covenant-0.0.65.dist-info/RECORD
