Metadata-Version: 2.1
Name: covenant
Version: 0.0.65
Summary: covenant
Home-page: https://github.com/decryptus/covenant
Author: Adrien Delle Cave
Author-email: pypi@doowan.net
License: License GPL-3
Platform: UNKNOWN
Classifier: License :: OSI Approved :: GNU General Public License v3 (GPLv3)
Classifier: Natural Language :: English
Classifier: Operating System :: Unix
Classifier: Programming Language :: Python
Classifier: Programming Language :: Python :: 2
Classifier: Programming Language :: Python :: 2.7
Classifier: Programming Language :: Python :: 3
Classifier: Programming Language :: Python :: 3.5
Classifier: Programming Language :: Python :: 3.6
Classifier: Programming Language :: Python :: 3.7
Classifier: Programming Language :: Python :: 3.9
Classifier: Topic :: System :: Monitoring
Classifier: Topic :: Utilities
Requires-Python: >=2.7, !=3.0.*, !=3.1.*, !=3.2.*, !=3.3.*, !=3.4.*
Requires-Dist: cryptography (>=3.2.1)
Requires-Dist: dwho (>=0.3.59)
Requires-Dist: httpdis (>=0.6.26)
Requires-Dist: jmespath (>=0.9.3)
Requires-Dist: packaging (>=19.0)
Requires-Dist: prometheus-client (>=0.6.0)
Requires-Dist: pyOpenSSL (>=20.0.0)
Requires-Dist: pycurl
Requires-Dist: pyjq (==2.3.1)
Requires-Dist: pyyaml (>=3.10)
Requires-Dist: requests (>=2.21.0)
Requires-Dist: six (>=1.13.0)
Requires-Dist: sonicprobe (>=0.3.51)
